qprsim/__init__.py
qprsim/config/__init__.py
qprsim/config/model_configuration.py
qprsim/config/modeling.py
qprsim/config/oc_model_configuration.py
qprsim/config/oc_modeling.py
qprsim/config/oc_parameter_implementations.py
qprsim/config/parameter_implementations.py
qprsim/config/impls/__init__.py
qprsim/config/oc/__init__.py
qprsim/core/__init__.py
qprsim/core/case.py
qprsim/core/event_system.py
qprsim/core/managers.py
qprsim/core/object_def.py
qprsim/core/oc_events.py
qprsim/core/oc_managers.py
qprsim/core/oc_schedulers.py
qprsim/core/oc/__init__.py
qprsim/execution/__init__.py
qprsim/execution/oc_simulation.py
qprsim/execution/oc_whatifs.py
qprsim/execution/simulation.py
qprsim/execution/whatifs.py
qprsim/execution/oc/__init__.py
qprsim/export/__init__.py
qprsim/export/exports.py
qprsim/export/filters.py
qprsim/export/oc_exports.py
qprsim/model/__init__.py
qprsim/model/conceptual_models.py
qprsim/model/graph_models.py
qprsim/model/model_data.py
qprsim/model/model_parameters.py
qprsim/model/model_traits.py
qprsim/model/oc_graph_models.py
qprsim/model/oc_model_data.py
qprsim/model/oc_model_parameters.py
qprsim/model/oc_model_traits.py
qprsim/model/oc_sim_graph.py
qprsim/model/oc_visualizer.py
qprsim/model/sim_graph.py
qprsim/model/visualizer.py
qprsim/model/oc/__init__.py
qprsim/shared/__init__.py
qprsim/shared/base_classes.py
qprsim/shared/enums.py
qprsim/shared/shared_traits.py
qprsim/utils/__init__.py
qprsim/utils/sampling.py
qprsim/utils/time_utils.py
qprsim/utils/utils.py
qprsim/utils/viz.py
qprsim-0.2.2.dist-info/METADATA
qprsim-0.2.2.dist-info/WHEEL
qprsim-0.2.2.dist-info/RECORD
