Metadata-Version: 2.4
Name: qprsim
Version: 0.2.2
Author-email: Leah Tacke genannt Unterberg <l.tgu@pads.rwth-aachen.de>
License-Expression: MIT
Requires-Python: <3.14,>=3.11
Requires-Dist: numpy<2,>=1.26
Requires-Dist: pandas<3,>=2.0
Requires-Dist: pm4py<3,>=2.7
